setup.cfg
setup.py
src/twitter/__init__.py
src/twitter.common.process.egg-info/PKG-INFO
src/twitter.common.process.egg-info/SOURCES.txt
src/twitter.common.process.egg-info/dependency_links.txt
src/twitter.common.process.egg-info/namespace_packages.txt
src/twitter.common.process.egg-info/requires.txt
src/twitter.common.process.egg-info/top_level.txt
src/twitter.common.process.egg-info/zip-safe
src/twitter/common/__init__.py
src/twitter/common/process/__init__.py
src/twitter/common/process/process_handle.py
src/twitter/common/process/process_handle_procfs.py
src/twitter/common/process/process_handle_ps.py
src/twitter/common/process/process_provider.py
src/twitter/common/process/process_provider_procfs.py
src/twitter/common/process/process_provider_ps.py